[
  {
    "data": {
      "03/02/2022": {
        "positive": 1,
        "negative": 1,
        "neutral": 30,
        "numPosts": 32
      },
      "03/03/2022": {
        "positive": 0,
        "negative": 1,
        "neutral": 40,
        "numPosts": 41
      },
      "03/04/2022": {
        "positive": 1,
        "negative": 0,
        "neutral": 72,
        "numPosts": 73
      },
      "03/05/2022": {
        "positive": 0,
        "negative": 1,
        "neutral": 45,
        "numPosts": 46
      },
      "03/06/2022": {
        "positive": 0,
        "negative": 2,
        "neutral": 32,
        "numPosts": 34
      },
      "03/07/2022": {
        "positive": 2,
        "negative": 3,
        "neutral": 94,
        "numPosts": 99
      },
      "03/08/2022": {
        "positive": 1,
        "negative": 2,
        "neutral": 25,
        "numPosts": 28
      }
    },
    "indicators": {
      "perc_inc": -0.12,
      "weekly_neutral": 338,
      "weekly_positive": 5,
      "weekly_negative": 10,
      "weekly_total": 353
    }
  }
]
